{
  "name": "cancelObjectStorage",
  "description": "Cancel Object Storage on an Account.\n\n**Warning**: Removes all buckets and their contents from your Account. This data is irretrievable once removed.\n",
  "parameters": {
    "type": "object"
  },
  "handler": "http",
  "request": {
    "method": "POST",
    "url": {
      "$uri": "https://api.linode.com/v4/object-storage/cancel"
    }
  },
  "responses": {
    "200": {
      "$encode": "markdown",
      "$block": [
        {
          "$h1": "Object"
        },
        {
          "$lang": "json",
          "$code": {
            "$encode": "json",
            "$indent": true,
            "$content": {
              "$": "$.body"
            }
          }
        }
      ]
    },
    "default": {
      "$encode": "markdown",
      "$block": [
        {
          "$h1": "Object"
        },
        "**Key properties:**",
        {
          "$ul": [
            "**errors**"
          ]
        },
        {
          "$lang": "json",
          "$code": {
            "$encode": "json",
            "$indent": true,
            "$content": {
              "$": "$.body"
            }
          }
        }
      ]
    }
  }
}
