{
  "name": "PostAs2Stations",
  "description": "Create As2 Station",
  "parameters": {
    "type": "object",
    "properties": {
      "body": {
        "properties": {
          "name": {
            "description": "AS2 Name",
            "type": "string",
            "x-ms-summary": "AS2 Name"
          },
          "private_key": {
            "type": "string",
            "x-ms-summary": null
          },
          "private_key_password": {
            "type": "string",
            "x-ms-summary": null
          },
          "public_certificate": {
            "type": "string",
            "x-ms-summary": null
          }
        },
        "required": [
          "name",
          "public_certificate",
          "private_key"
        ],
        "type": "object"
      }
    },
    "required": [
      "body"
    ]
  },
  "handler": "http",
  "request": {
    "method": "POST",
    "url": {
      "$uri": "//app.files.com/api/rest/v1/as2_stations"
    },
    "body": {
      "$": "body",
      "encode": "multipart"
    }
  },
  "responses": {
    "201": {
      "$encode": "markdown",
      "$block": [
        {
          "$h1": "Object"
        },
        "Create As2 Station",
        "**Key properties:**",
        {
          "$ul": [
            "**domain**: The station's AS2 domain name.",
            "**hex_public_certificate_serial**: Serial of public certificate used for message security in hex format.",
            "**id**: Id of the AS2 Station.",
            "**name**: The station's formal AS2 name.",
            "**private_key_md5**: MD5 hash of private key used for message security.",
            "**private_key_password_md5**: MD5 hash of private key password used for message security.",
            "**public_certificate_issuer**: Issuer of public certificate used for message security.",
            "**public_certificate_md5**: MD5 hash of public certificate used for message security.",
            "**public_certificate_not_after**: Not after value of public certificate used for message security.",
            "**public_certificate_not_before**: Not before value of public certificate used for message security.",
            "**public_certificate_serial**: Serial of public certificate used for message security.",
            "**public_certificate_subject**: Subject of public certificate used for message security.",
            "**uri**: Public URI for sending AS2 message to."
          ]
        },
        {
          "$lang": "json",
          "$code": {
            "$encode": "json",
            "$indent": true,
            "$content": {
              "$": "$.body"
            }
          }
        }
      ]
    }
  }
}
