{
  "name": "identityVerificationList",
  "description": "Filter and list Identity Verifications created by your account",
  "parameters": {
    "type": "object",
    "properties": {
      "body": {
        "$ref": "#/$defs/IdentityVerificationListRequest"
      }
    },
    "required": [
      "body"
    ],
    "$defs": {
      "IdentityVerificationListRequest": {
        "description": "Request input for listing identity verifications",
        "properties": {
          "client_id": {
            "$ref": "#/$defs/APIClientID"
          },
          "client_user_id": {
            "$ref": "#/$defs/ClientUserID"
          },
          "cursor": {
            "$ref": "#/$defs/Cursor"
          },
          "secret": {
            "$ref": "#/$defs/APISecret"
          },
          "template_id": {
            "$ref": "#/$defs/IdentityVerificationTemplateID"
          }
        },
        "required": [
          "template_id",
          "client_user_id"
        ],
        "type": "object"
      },
      "APIClientID": {
        "description": "Your Plaid API `client_id`. The `client_id` is required and may be provided either in the `PLAID-CLIENT-ID` header or as part of a request body.",
        "title": "ClientID",
        "type": "string"
      },
      "ClientUserID": {
        "description": "An identifier to help you connect this object to your internal systems. For example, your database ID corresponding to this object.",
        "example": "your-db-id-3b24110",
        "minLength": 1,
        "title": "ClientUserID",
        "type": "string"
      },
      "Cursor": {
        "description": "An identifier that determines which page of results you receive.",
        "example": "eyJkaXJlY3Rpb24iOiJuZXh0Iiwib2Zmc2V0IjoiMTU5NDM",
        "nullable": true,
        "type": "string"
      },
      "APISecret": {
        "description": "Your Plaid API `secret`. The `secret` is required and may be provided either in the `PLAID-SECRET` header or as part of a request body.",
        "title": "APISecret",
        "type": "string"
      },
      "IdentityVerificationTemplateID": {
        "description": "ID of the associated Identity Verification template.",
        "example": "idvtmp_4FrXJvfQU3zGUR",
        "title": "IdentityVerificationTemplateID",
        "type": "string"
      }
    }
  },
  "handler": "http",
  "request": {
    "method": "POST",
    "url": {
      "$uri": "https://production.plaid.com/identity_verification/list"
    },
    "body": {
      "$": "body",
      "encode": "json"
    }
  },
  "responses": {
    "200": {
      "$encode": "markdown",
      "$block": [
        {
          "$h1": "Object"
        },
        "Paginated list of Plaid sessions.",
        "**Key properties:**",
        {
          "$ul": [
            "**identity_verifications**: List of Plaid sessions",
            "**next_cursor**: An identifier that determines which page of results you receive.",
            "**request_id**: A unique identifier for the request, which can be used for troubleshooting. This identifier, like all Plaid identifiers, is case sensitive."
          ]
        },
        {
          "$lang": "json",
          "$code": {
            "$encode": "json",
            "$indent": true,
            "$content": {
              "$": "$.body"
            }
          }
        }
      ]
    }
  }
}
