{
  "name": "bulkGetGroups",
  "description": "Returns a [paginated](#pagination) list of groups.\n\n**[Permissions](#permissions) required:** *Browse users and groups* [global permission](https://confluence.atlassian.com/x/x4dKLg).",
  "parameters": {
    "type": "object",
    "properties": {
      "startAt": {
        "default": 0,
        "format": "int64",
        "type": "integer",
        "description": "The index of the first item to return in a page of results (page offset)."
      },
      "maxResults": {
        "default": 50,
        "format": "int32",
        "type": "integer",
        "description": "The maximum number of items to return per page."
      },
      "groupId": {
        "example": "3571b9a7-348f-414a-9087-8e1ea03a7df8",
        "items": {
          "example": "3571b9a7-348f-414a-9087-8e1ea03a7df8",
          "type": "string"
        },
        "type": "array",
        "uniqueItems": true,
        "description": "The ID of a group. To specify multiple IDs, pass multiple `groupId` parameters. For example, `groupId=5b10a2844c20165700ede21g&groupId=5b10ac8d82e05b22cc7d4ef5`."
      },
      "groupName": {
        "items": {
          "type": "string"
        },
        "type": "array",
        "uniqueItems": true,
        "description": "The name of a group. To specify multiple names, pass multiple `groupName` parameters. For example, `groupName=administrators&groupName=jira-software-users`."
      },
      "accessType": {
        "type": "string",
        "description": "The access level of a group. Valid values: 'site-admin', 'admin', 'user'."
      },
      "applicationKey": {
        "type": "string",
        "description": "The application key of the product user groups to search for. Valid values: 'jira-servicedesk', 'jira-software', 'jira-product-discovery', 'jira-core'."
      }
    }
  },
  "handler": "http",
  "request": {
    "method": "GET",
    "url": {
      "$uri": "https://your-domain.atlassian.net/rest/api/3/group/bulk{?startAt,maxResults,groupId,groupName,accessType,applicationKey}"
    }
  },
  "responses": {
    "200": {
      "$encode": "markdown",
      "$block": [
        {
          "$h1": "Object"
        },
        "A page of items.",
        "**Key properties:**",
        {
          "$ul": [
            "**isLast**: Whether this is the last page.",
            "**maxResults**: The maximum number of items that could be returned.",
            "**nextPage**: If there is another page of results, the URL of the next page.",
            "**self**: The URL of the page.",
            "**startAt**: The index of the first item returned.",
            "**total**: The number of items returned.",
            "**values**: The list of items."
          ]
        },
        {
          "$lang": "json",
          "$code": {
            "$encode": "json",
            "$indent": true,
            "$content": {
              "$": "$.body"
            }
          }
        }
      ]
    }
  }
}
