{
  "name": "recipeNutritionByIDImage",
  "description": "Visualize a recipe's nutritional information as an image.",
  "parameters": {
    "type": "object",
    "properties": {
      "id": {
        "example": 1082038,
        "type": "number",
        "description": "The recipe id."
      }
    },
    "required": [
      "id"
    ]
  },
  "handler": "http",
  "request": {
    "method": "GET",
    "url": {
      "$uri": "https://api.spoonacular.com/recipes/{id}/nutritionWidget.png"
    }
  },
  "responses": {
    "200": {
      "$encode": "markdown",
      "$block": [
        {
          "$h1": "Object"
        },
        {
          "$lang": "json",
          "$code": {
            "$encode": "json",
            "$indent": true,
            "$content": {
              "$": "$.body"
            }
          }
        }
      ]
    }
  }
}
