{
  "name": "ListReportsForReportGroup",
  "description": " Returns a list of ARNs for the reports that belong to a <code>ReportGroup</code>. ",
  "parameters": {
    "type": "object",
    "properties": {
      "maxResults": {
        "type": "string",
        "description": "Pagination limit"
      },
      "nextToken": {
        "type": "string",
        "description": "Pagination token"
      },
      "X-Amz-Target": {
        "type": "string",
        "enum": [
          "CodeBuild_20161006.ListReportsForReportGroup"
        ]
      },
      "X-Amz-Content-Sha256": {
        "type": "string"
      },
      "X-Amz-Date": {
        "type": "string"
      },
      "X-Amz-Algorithm": {
        "type": "string"
      },
      "X-Amz-Credential": {
        "type": "string"
      },
      "X-Amz-Security-Token": {
        "type": "string"
      },
      "X-Amz-Signature": {
        "type": "string"
      },
      "X-Amz-SignedHeaders": {
        "type": "string"
      },
      "body": {
        "$ref": "#/$defs/ListReportsForReportGroupInput"
      }
    },
    "required": [
      "X-Amz-Target",
      "body"
    ],
    "$defs": {
      "ListReportsForReportGroupInput": {
        "type": "object",
        "required": [
          "reportGroupArn"
        ],
        "title": "ListReportsForReportGroupInput",
        "properties": {
          "reportGroupArn": {
            "allOf": [
              {
                "$ref": "#/$defs/String"
              },
              {
                "description": " The ARN of the report group for which you want to return report ARNs. "
              }
            ]
          },
          "nextToken": {
            "allOf": [
              {
                "$ref": "#/$defs/String"
              },
              {
                "description": " During a previous call, the maximum number of items that can be returned is the value specified in <code>maxResults</code>. If there more items in the list, then a unique string called a <i>nextToken</i> is returned. To get the next batch of items in the list, call this operation again, adding the next token to the call. To get all of the items in the list, keep calling this operation with each subsequent next token that is returned, until no more next tokens are returned. "
              }
            ]
          },
          "sortOrder": {
            "allOf": [
              {
                "$ref": "#/$defs/SortOrderType"
              },
              {
                "description": " Use to specify whether the results are returned in ascending or descending order. "
              }
            ]
          },
          "maxResults": {
            "allOf": [
              {
                "$ref": "#/$defs/PageSize"
              },
              {
                "description": " The maximum number of paginated reports in this report group returned per response. Use <code>nextToken</code> to iterate pages in the list of returned <code>Report</code> objects. The default value is 100. "
              }
            ]
          },
          "filter": {
            "allOf": [
              {
                "$ref": "#/$defs/ReportFilter"
              },
              {
                "description": " A <code>ReportFilter</code> object used to filter the returned reports. "
              }
            ]
          }
        }
      },
      "String": {
        "type": "string"
      },
      "SortOrderType": {
        "type": "string",
        "enum": [
          "ASCENDING",
          "DESCENDING"
        ]
      },
      "PageSize": {
        "type": "integer",
        "minimum": 1,
        "maximum": 100
      },
      "ReportFilter": {
        "type": "object",
        "properties": {
          "status": {
            "allOf": [
              {
                "$ref": "#/$defs/ReportStatusType"
              },
              {
                "description": " The status used to filter reports. You can filter using one status only. "
              }
            ]
          }
        },
        "description": " A filter used to return reports with the status specified by the input <code>status</code> parameter. "
      },
      "ReportStatusType": {
        "type": "string",
        "enum": [
          "GENERATING",
          "SUCCEEDED",
          "FAILED",
          "INCOMPLETE",
          "DELETING"
        ]
      }
    }
  },
  "handler": "http",
  "request": {
    "method": "POST",
    "url": {
      "$uri": "http://codebuild.us-east-1.amazonaws.com/#X-Amz-Target=CodeBuild_20161006.ListReportsForReportGroup{?maxResults,nextToken}"
    },
    "headers": {
      "X-Amz-Target": {
        "$": "X-Amz-Target"
      },
      "X-Amz-Content-Sha256": {
        "$": "X-Amz-Content-Sha256"
      },
      "X-Amz-Date": {
        "$": "X-Amz-Date"
      },
      "X-Amz-Algorithm": {
        "$": "X-Amz-Algorithm"
      },
      "X-Amz-Credential": {
        "$": "X-Amz-Credential"
      },
      "X-Amz-Security-Token": {
        "$": "X-Amz-Security-Token"
      },
      "X-Amz-Signature": {
        "$": "X-Amz-Signature"
      },
      "X-Amz-SignedHeaders": {
        "$": "X-Amz-SignedHeaders"
      }
    },
    "body": {
      "$": "body",
      "encode": "json"
    }
  },
  "responses": {
    "200": {
      "$encode": "markdown",
      "$block": [
        {
          "$h1": "Object"
        },
        "**Key properties:**",
        {
          "$ul": [
            "**nextToken**",
            "**reports**"
          ]
        },
        {
          "$lang": "json",
          "$code": {
            "$encode": "json",
            "$indent": true,
            "$content": {
              "$": "$.body"
            }
          }
        }
      ]
    },
    "480": {
      "$encode": "markdown",
      "$lang": "json",
      "$code": {
        "$encode": "json",
        "$indent": true,
        "$content": {
          "$": "$.body"
        }
      }
    },
    "481": {
      "$encode": "markdown",
      "$lang": "json",
      "$code": {
        "$encode": "json",
        "$indent": true,
        "$content": {
          "$": "$.body"
        }
      }
    }
  }
}
