{
  "name": "StopTrainingJob",
  "description": "<p>Stops a training job. To stop a job, SageMaker sends the algorithm the <code>SIGTERM</code> signal, which delays job termination for 120 seconds. Algorithms might use this 120-second window to save the model artifacts, so the results of the training is not lost. </p> <p>When it receives a <code>StopTrainingJob</code> request, SageMaker changes the status of the job to <code>Stopping</code>. After SageMaker stops the job, it sets the status to <code>Stopped</code>.</p>",
  "parameters": {
    "type": "object",
    "properties": {
      "X-Amz-Target": {
        "type": "string",
        "enum": [
          "SageMaker.StopTrainingJob"
        ]
      },
      "X-Amz-Content-Sha256": {
        "type": "string"
      },
      "X-Amz-Date": {
        "type": "string"
      },
      "X-Amz-Algorithm": {
        "type": "string"
      },
      "X-Amz-Credential": {
        "type": "string"
      },
      "X-Amz-Security-Token": {
        "type": "string"
      },
      "X-Amz-Signature": {
        "type": "string"
      },
      "X-Amz-SignedHeaders": {
        "type": "string"
      },
      "body": {
        "$ref": "#/$defs/StopTrainingJobRequest"
      }
    },
    "required": [
      "X-Amz-Target",
      "body"
    ],
    "$defs": {
      "StopTrainingJobRequest": {
        "type": "object",
        "required": [
          "TrainingJobName"
        ],
        "title": "StopTrainingJobRequest",
        "properties": {
          "TrainingJobName": {
            "allOf": [
              {
                "$ref": "#/$defs/TrainingJobName"
              },
              {
                "description": "The name of the training job to stop."
              }
            ]
          }
        }
      },
      "TrainingJobName": {
        "type": "string",
        "pattern": "^[a-zA-Z0-9](-*[a-zA-Z0-9]){0,62}",
        "minLength": 1,
        "maxLength": 63
      }
    }
  },
  "handler": "http",
  "request": {
    "method": "POST",
    "url": {
      "$uri": "http://api.sagemaker.us-east-1.amazonaws.com/#X-Amz-Target=SageMaker.StopTrainingJob"
    },
    "headers": {
      "X-Amz-Target": {
        "$": "X-Amz-Target"
      },
      "X-Amz-Content-Sha256": {
        "$": "X-Amz-Content-Sha256"
      },
      "X-Amz-Date": {
        "$": "X-Amz-Date"
      },
      "X-Amz-Algorithm": {
        "$": "X-Amz-Algorithm"
      },
      "X-Amz-Credential": {
        "$": "X-Amz-Credential"
      },
      "X-Amz-Security-Token": {
        "$": "X-Amz-Security-Token"
      },
      "X-Amz-Signature": {
        "$": "X-Amz-Signature"
      },
      "X-Amz-SignedHeaders": {
        "$": "X-Amz-SignedHeaders"
      }
    },
    "body": {
      "$": "body",
      "encode": "json"
    }
  },
  "responses": {
    "480": {
      "$encode": "markdown",
      "$lang": "json",
      "$code": {
        "$encode": "json",
        "$indent": true,
        "$content": {
          "$": "$.body"
        }
      }
    }
  }
}
