{
  "name": "sendEmailsExpenses",
  "description": "Bulk delete expenses",
  "parameters": {
    "type": "object",
    "properties": {
      "body": {
        "$ref": "#/components/schemas/BulkActionRequestBody",
        "description": "expense ids"
      }
    },
    "required": [
      "body"
    ]
  },
  "handler": "http",
  "request": {
    "method": "DELETE",
    "url": {
      "$uri": "https://app.apacta.com/api/v1/expenses/sendEmails"
    },
    "body": {
      "$": "body",
      "encode": "json"
    }
  },
  "responses": {
    "200": {
      "$encode": "markdown",
      "$block": [
        {
          "$h1": "Object"
        },
        "**Key properties:**",
        {
          "$ul": [
            "**data**",
            "**success**"
          ]
        },
        {
          "$lang": "json",
          "$code": {
            "$encode": "json",
            "$indent": true,
            "$content": {
              "$": "$.body"
            }
          }
        }
      ]
    },
    "400": {
      "$encode": "markdown",
      "$block": [
        {
          "$h1": "BadRequestResponse"
        },
        "**Key properties:**",
        {
          "$ul": [
            [
              "**data**",
              {
                "$ul": [
                  "**code** (default: 400)",
                  "**message**",
                  "**url**"
                ]
              }
            ],
            "**success** (default: false)"
          ]
        },
        {
          "$lang": "json",
          "$code": {
            "$encode": "json",
            "$indent": true,
            "$content": {
              "$": "$.body"
            }
          }
        }
      ]
    }
  }
}
