{
  "name": "PostNewBatchJob",
  "description": "Adds a new Batch job to the queue and returns the job info",
  "parameters": {
    "type": "object",
    "properties": {
      "Authorization": {
        "default": "Auto",
        "format": "string",
        "type": "string",
        "description": "The OAuth 1 authorization header. &apos;Auto&apos; enables auto complete."
      },
      "Api-Version": {
        "default": "default",
        "format": "string",
        "type": "string",
        "description": "The version of the api to target. Omit or set as &apos;default&apos; to target the current api version."
      },
      "body": {
        "$ref": "#/components/schemas/BatchJobInstruction",
        "description": "The the batch job instruction object."
      }
    },
    "required": [
      "Authorization",
      "Api-Version",
      "body"
    ]
  },
  "handler": "http",
  "request": {
    "method": "POST",
    "url": {
      "$uri": "https://api.test.payrun.io/Jobs/Batch"
    },
    "headers": {
      "Authorization": {
        "$": "Authorization"
      },
      "Api-Version": {
        "$": "Api-Version"
      }
    },
    "body": {
      "$": "body",
      "encode": "json"
    }
  },
  "responses": {
    "201": {
      "$encode": "markdown",
      "$block": [
        {
          "$h1": "Object"
        },
        "**Key properties:**",
        {
          "$ul": [
            [
              "**Link**",
              {
                "$ul": [
                  "**@href**: The links' href",
                  "**@rel**: The links' target type",
                  "**@title**: The links' title"
                ]
              }
            ]
          ]
        },
        {
          "$lang": "json",
          "$code": {
            "$encode": "json",
            "$indent": true,
            "$content": {
              "$": "$.body"
            }
          }
        }
      ]
    },
    "400": {
      "$encode": "markdown",
      "$block": [
        {
          "$h1": "Object"
        },
        "**Key properties:**",
        {
          "$ul": [
            [
              "**ErrorModel**",
              {
                "$ul": [
                  "**Description**: The error models' description",
                  "**ErrorCategory**: The error models' error category",
                  [
                    "**Errors**: The error models' errors",
                    {
                      "$ul": [
                        "**Error**"
                      ]
                    }
                  ]
                ]
              }
            ]
          ]
        },
        {
          "$lang": "json",
          "$code": {
            "$encode": "json",
            "$indent": true,
            "$content": {
              "$": "$.body"
            }
          }
        }
      ]
    },
    "401": {
      "$encode": "markdown",
      "$block": [
        {
          "$h1": "Object"
        },
        "**Key properties:**",
        {
          "$ul": [
            [
              "**ErrorModel**",
              {
                "$ul": [
                  "**Description**: The error models' description",
                  "**ErrorCategory**: The error models' error category",
                  [
                    "**Errors**: The error models' errors",
                    {
                      "$ul": [
                        "**Error**"
                      ]
                    }
                  ]
                ]
              }
            ]
          ]
        },
        {
          "$lang": "json",
          "$code": {
            "$encode": "json",
            "$indent": true,
            "$content": {
              "$": "$.body"
            }
          }
        }
      ]
    },
    "404": {
      "$encode": "markdown",
      "$block": [
        {
          "$h1": "Object"
        },
        "**Key properties:**",
        {
          "$ul": [
            [
              "**ErrorModel**",
              {
                "$ul": [
                  "**Description**: The error models' description",
                  "**ErrorCategory**: The error models' error category",
                  [
                    "**Errors**: The error models' errors",
                    {
                      "$ul": [
                        "**Error**"
                      ]
                    }
                  ]
                ]
              }
            ]
          ]
        },
        {
          "$lang": "json",
          "$code": {
            "$encode": "json",
            "$indent": true,
            "$content": {
              "$": "$.body"
            }
          }
        }
      ]
    },
    "500": {
      "$encode": "markdown",
      "$block": [
        {
          "$h1": "Object"
        },
        "**Key properties:**",
        {
          "$ul": [
            [
              "**ErrorModel**",
              {
                "$ul": [
                  "**Description**: The error models' description",
                  "**ErrorCategory**: The error models' error category",
                  [
                    "**Errors**: The error models' errors",
                    {
                      "$ul": [
                        "**Error**"
                      ]
                    }
                  ]
                ]
              }
            ]
          ]
        },
        {
          "$lang": "json",
          "$code": {
            "$encode": "json",
            "$indent": true,
            "$content": {
              "$": "$.body"
            }
          }
        }
      ]
    }
  }
}
