{
  "name": "Brands_PostBrands",
  "description": "This method creates one or more brand profile files for an account.\n\nTo specify logos for the brand,\nuse the\n[AccountBrands: updateLogo](/docs/esign-rest-api/reference/accounts/accountbrands/updatelogo/)\nmethod\nafter you create the brand.\n\n\nEither or both of the following settings must be enabled for the account to use this method:\n\n- `canSelfBrandSign`\n- `canSelfBrandSend`\n\n### Related topics\n\n- [How to create a brand](/docs/esign-rest-api/how-to/create-brand/)\n",
  "parameters": {
    "type": "object",
    "properties": {
      "accountId": {
        "type": "string",
        "description": "The external account number (int) or account ID GUID."
      },
      "body": {
        "$ref": "#/$defs/brand"
      }
    },
    "required": [
      "accountId"
    ],
    "$defs": {
      "brand": {
        "description": "Information about a brand that is associated with an account. A brand applies custom styles and text to an envelope.",
        "properties": {
          "brandCompany": {
            "description": "The name of the company associated with the brand.",
            "type": "string"
          },
          "brandId": {
            "description": "The ID used to identify a specific brand in API calls.",
            "type": "string"
          },
          "brandLanguages": {
            "description": "An array of two-letter codes for the languages that you want to use with the brand. The supported languages are:\n\n- Arabic (`ar`)\n- Armenian (`hy`)\n- Bahasa Indonesia (`id`)\n- Bahasa Malay (`ms`)\n- Bulgarian (`bg`)\n- Chinese Simplified (`zh_CN`)\n- Chinese Traditional (`zh_TW`)\n- Croatian (`hr`)\n- Czech (`cs`)\n- Danish (`da`)\n- Dutch (`nl`)\n- English UK (`en_GB`)\n- English US (`en`)\n- Estonian (`et`)\n- Farsi (`fa`)\n- Finnish (`fi`)\n- French (`fr`)\n- French Canada (`fr_CA`)\n- German (`de`)\n- Greek (`el`)\n- Hebrew (`he`)\n- Hindi (`hi`)\n- Hungarian (`hu`)\n- Italian (`it`)\n- Japanese (`ja`)\n- Korean (`ko`)\n- Latvian (`lv`)\n- Lithuanian (`lt`)\n- Norwegian (`no`)\n- Polish (`pl`)\n- Portuguese (`pt`)\n- Portuguese Brasil (`pt_BR`)\n- Romanian (`ro`)\n- Russian (`ru`)\n- Serbian (`sr`)\n- Slovak (`sk`)\n- Slovenian (`sl`)\n- Spanish (`es`)\n- Spanish Latin America (`es_MX`)\n- Swedish (`sv`)\n- Thai (`th`)\n- Turkish (`tr`)\n- Ukranian (`uk`)\n- Vietnamese (`vi`)",
            "items": {
              "type": "string"
            },
            "type": "array"
          },
          "brandName": {
            "description": "The name of the brand.",
            "type": "string"
          },
          "colors": {
            "description": "An array of name-value pairs specifying the colors that the brand uses for the following elements:\n\n- Button background\n- Button text\n- Header background\n- Header text",
            "items": {
              "$ref": "#/$defs/nameValue"
            },
            "type": "array"
          },
          "defaultBrandLanguage": {
            "description": "The two-letter code for the language that you want to use as the brand default. The supported languages are:\n\n- Arabic (`ar`)\n- Armenian (`hy`)\n- Bahasa Indonesia (`id`)\n- Bahasa Malay (`ms`)\n- Bulgarian (`bg`)\n- Chinese Simplified (`zh_CN`)\n- Chinese Traditional (`zh_TW`)\n- Croatian (`hr`)\n- Czech (`cs`)\n- Danish (`da`)\n- Dutch (`nl`)\n- English UK (`en_GB`)\n- English US (`en`)\n- Estonian (`et`)\n- Farsi (`fa`)\n- Finnish (`fi`)\n- French (`fr`)\n- French Canada (`fr_CA`)\n- German (`de`)\n- Greek (`el`)\n- Hebrew (`he`)\n- Hindi (`hi`)\n- Hungarian (`hu`)\n- Italian (`it`)\n- Japanese (`ja`)\n- Korean (`ko`)\n- Latvian (`lv`)\n- Lithuanian (`lt`)\n- Norwegian (`no`)\n- Polish (`pl`)\n- Portuguese (`pt`)\n- Portuguese Brasil (`pt_BR`)\n- Romanian (`ro`)\n- Russian (`ru`)\n- Serbian (`sr`)\n- Slovak (`sk`)\n- Slovenian (`sl`)\n- Spanish (`es`)\n- Spanish Latin America (`es_MX`)\n- Swedish (`sv`)\n- Thai (`th`)\n- Turkish (`tr`)\n- Ukranian (`uk`)\n- Vietnamese (`vi`)",
            "type": "string"
          },
          "emailContent": {
            "description": "Deprecated.",
            "items": {
              "$ref": "#/$defs/brandEmailContent"
            },
            "type": "array"
          },
          "errorDetails": {
            "$ref": "#/$defs/errorDetails"
          },
          "isOverridingCompanyName": {
            "description": "When **true,** the `brandCompany` property is overriding the name of the company in the account settings.",
            "type": "boolean"
          },
          "isSendingDefault": {
            "description": "When **true,** the sending brand is the default brand for sending new envelopes.",
            "type": "boolean"
          },
          "isSigningDefault": {
            "description": "When **true,** the siging brand is the default brand for the signing experience.",
            "type": "boolean"
          },
          "landingPages": {
            "description": "An array of name/value pairs specifying the pages to which the user is redirected after the following events occur:\n\n- Signing Completed\n- Viewed Exit\n- Finish Later\n- Decline\n- Session Timeout\n- Authentication Failure\n\nIf you do not specify landing pages, the DocuSign default pages are used.",
            "items": {
              "$ref": "#/$defs/nameValue"
            },
            "type": "array"
          },
          "links": {
            "description": "An array of `brandLink` objects that contain information about the links that the brand uses.",
            "items": {
              "$ref": "#/$defs/brandLink"
            },
            "type": "array"
          },
          "logos": {
            "$ref": "#/$defs/brandLogos"
          },
          "resources": {
            "$ref": "#/$defs/brandResourceUrls"
          }
        },
        "type": "object",
        "x-ds-definition-name": "brand",
        "x-ms-summary": "Information about a brand that is associated with an account. A brand applies custom styles and text to an envelope."
      },
      "nameValue": {
        "description": "A name-value pair that describes an item and provides a value for the item.",
        "properties": {
          "errorDetails": {
            "$ref": "#/$defs/errorDetails"
          },
          "name": {
            "description": "The name of the item.",
            "type": "string"
          },
          "originalValue": {
            "description": "The initial value of the item.",
            "type": "string"
          },
          "value": {
            "description": "The current value of the item.",
            "type": "string"
          }
        },
        "type": "object",
        "x-ds-definition-name": "nameValue",
        "x-ms-summary": "A name-value pair that describes an item and provides a value for the item."
      },
      "errorDetails": {
        "description": "This object describes errors that occur. It is only valid for responses and ignored in requests.",
        "properties": {
          "errorCode": {
            "description": "The code associated with the error condition.",
            "type": "string"
          },
          "message": {
            "description": "A brief message describing the error condition.",
            "type": "string"
          }
        },
        "type": "object",
        "x-ds-definition-name": "errorDetails",
        "x-ms-summary": "This object describes errors that occur. It is only valid for responses and ignored in requests."
      },
      "brandEmailContent": {
        "description": "Deprecated.",
        "properties": {
          "content": {
            "description": "Deprecated.",
            "type": "string"
          },
          "emailContentType": {
            "description": "Deprecated.",
            "type": "string"
          },
          "emailToLink": {
            "description": "Deprecated.",
            "type": "string"
          },
          "linkText": {
            "description": "Deprecated.",
            "type": "string"
          }
        },
        "type": "object",
        "x-ds-definition-name": "brandEmailContent",
        "x-ms-summary": "Deprecated."
      },
      "brandLink": {
        "description": "Information about a link that a brand uses.",
        "properties": {
          "linkText": {
            "description": "The text used for the link.",
            "type": "string"
          },
          "linkType": {
            "description": "The type of link. Valid values include:\n\n- `aboutDocusign`\n- `closeButton`",
            "type": "string"
          },
          "showLink": {
            "description": "When **true,** the link displays to the recipient.",
            "type": "string"
          },
          "urlOrMailTo": {
            "description": "The URL or mailto address of the link.",
            "type": "string"
          }
        },
        "type": "object",
        "x-ds-definition-name": "brandLink",
        "x-ms-summary": "Information about a link that a brand uses."
      },
      "brandLogos": {
        "description": "The URIs for retrieving the logos that are associated with the brand.\n\nThese are read-only properties that provide a URI to logos in use.\nTo update a logo use\n[AccountBrands: updateLogo](/docs/esign-rest-api/reference/accounts/accountbrands/updatelogo/).\n",
        "properties": {
          "email": {
            "description": "The URI for the brand's secondary logo.\n\nThis is a read-only property that provides a URI to the logo in use.\nTo update a logo use\n[AccountBrands: updateLogo](/docs/esign-rest-api/reference/accounts/accountbrands/updatelogo/).\n",
            "type": "string"
          },
          "primary": {
            "description": "The URI for the brand's secondary logo.\n\nThis is a read-only property that provides a URI to the logo in use.\nTo update a logo use\n[AccountBrands: updateLogo](/docs/esign-rest-api/reference/accounts/accountbrands/updatelogo/).\n",
            "type": "string"
          },
          "secondary": {
            "description": "The URI for the brand's secondary logo.\n\nThis is a read-only property that provides a URI to the logo in use.\nTo update a logo use\n[AccountBrands: updateLogo](/docs/esign-rest-api/reference/accounts/accountbrands/updatelogo/).\n",
            "type": "string"
          }
        },
        "type": "object",
        "x-ds-definition-name": "brandLogos",
        "x-ms-summary": "The URIs for retrieving the logos that are associated with the brand.\n\nThese are read-only properties that provide a URI to logos in use.\nTo update a logo use\n[AccountBrands: updateLogo](/docs/esign-rest-api/reference/accounts/accountbrands/updatelogo/).\n"
      },
      "brandResourceUrls": {
        "description": "Brands use resource files to style the following experiences: \n\n- Email\n- Sending\n- Signing\n- Captive (embedded) signing \n\nYou can modify these resource files to customize these experiences.",
        "properties": {
          "email": {
            "description": "The URI for the email resource file that the brand uses.",
            "type": "string"
          },
          "sending": {
            "description": "The URI for the sending resource file that the brand uses.",
            "type": "string"
          },
          "signing": {
            "description": "The URI for the signing resource file that the brand uses.",
            "type": "string"
          },
          "signingCaptive": {
            "description": "The URI for the captive (embedded) signing resource file that the brand uses.",
            "type": "string"
          }
        },
        "type": "object",
        "x-ds-definition-name": "brandResourceUrls",
        "x-ms-summary": "Brands use resource files to style the following experiences: \n\n- Email\n- Sending\n- Signing\n- Captive (embedded) signing \n\nYou can modify these resource files to customize these experiences."
      }
    }
  },
  "handler": "http",
  "request": {
    "method": "POST",
    "url": {
      "$uri": "https://www.docusign.net/restapi/v2.1/accounts/{accountId}/brands"
    },
    "body": {
      "$": "body",
      "encode": "json"
    }
  },
  "responses": {
    "201": {
      "$encode": "markdown",
      "$block": [
        {
          "$h1": "Object"
        },
        "The AccountBrands resource enables you to use account-level brands to customize the styles and text that recipients see.",
        "**Key properties:**",
        {
          "$ul": [
            "**brands**: A list of brands.",
            "**recipientBrandIdDefault**: The brand that envelope recipients see when a brand is not explicitly set.",
            "**senderBrandIdDefault**: The brand that envelope senders see when a brand is not explicitly set."
          ]
        },
        {
          "$lang": "json",
          "$code": {
            "$encode": "json",
            "$indent": true,
            "$content": {
              "$": "$.body"
            }
          }
        }
      ]
    },
    "400": {
      "$encode": "markdown",
      "$block": [
        {
          "$h1": "Object"
        },
        "This object describes errors that occur. It is only valid for responses and ignored in requests.",
        "**Key properties:**",
        {
          "$ul": [
            "**errorCode**: The code associated with the error condition.",
            "**message**: A brief message describing the error condition."
          ]
        },
        {
          "$lang": "json",
          "$code": {
            "$encode": "json",
            "$indent": true,
            "$content": {
              "$": "$.body"
            }
          }
        }
      ]
    }
  }
}
