{
  "name": "getOrganisationsIdAddonprovidersProviderIdPlansPlanId",
  "parameters": {
    "type": "object",
    "properties": {
      "id": {
        "type": "string"
      },
      "providerId": {
        "type": "string"
      },
      "planId": {
        "type": "string"
      }
    },
    "required": [
      "id",
      "providerId",
      "planId"
    ]
  },
  "handler": "http",
  "request": {
    "method": "GET",
    "url": {
      "$uri": "https://api.clever-cloud.com/v2/organisations/{id}/addonproviders/{providerId}/plans/{planId}"
    }
  },
  "responses": {
    "200": {
      "$encode": "markdown",
      "$block": [
        {
          "$h1": "Object"
        },
        "**Key properties:**",
        {
          "$ul": [
            "**features**: The list of the feature in the addon",
            "**id**: `plan_${uuid}`",
            "**name**: Name of the pan",
            "**price**",
            "**slug**"
          ]
        },
        {
          "$lang": "json",
          "$code": {
            "$encode": "json",
            "$indent": true,
            "$content": {
              "$": "$.body"
            }
          }
        }
      ]
    }
  }
}
